mcp_lcu_server/__init__.py
mcp_lcu_server/config.py
mcp_lcu_server/main.py
mcp_lcu_server/server.py
mcp_lcu_server-0.1.1.dist-info/licenses/LICENSE
mcp_lcu_server-0.1.1.dist-info/METADATA
mcp_lcu_server-0.1.1.dist-info/WHEEL
mcp_lcu_server-0.1.1.dist-info/entry_points.txt
mcp_lcu_server-0.1.1.dist-info/top_level.txt
mcp_lcu_server-0.1.1.dist-info/RECORD
