Metadata-Version: 2.4
Name: mcp_lcu_server
Version: 0.1.1
Summary: MCP Linux Common Utility Server
Author-email: Lewis Guo <guolisen@gmail.com>
License: MIT License
Requires-Python: >=3.10
License-File: LICENSE
Requires-Dist: mcp>=0.1.0
Requires-Dist: pydantic>=2.0.0
Requires-Dist: pydantic-settings>=2.0.0
Requires-Dist: psutil>=5.9.0
Requires-Dist: py-cpuinfo>=9.0.0
Requires-Dist: netifaces>=0.11.0
Requires-Dist: requests>=2.28.0
Requires-Dist: paramiko>=3.0.0
Requires-Dist: pyudev>=0.24.0
Requires-Dist: click>=8.1.0
Requires-Dist: PyYAML>=6.0
Requires-Dist: asyncio>=3.4.3
Requires-Dist: setuptools>=78.1.0
Requires-Dist: wheel>=0.45.1
Requires-Dist: twine>=6.1.0
Requires-Dist: pkginfo>=1.12.1.2
Requires-Dist: urllib3>=2.3.0
Requires-Dist: requests-toolbelt>=1.0.0
Requires-Dist: build>=1.2.2.post1
Provides-Extra: dev
Requires-Dist: pytest>=7.0.0; extra == "dev"
Requires-Dist: pytest-cov>=4.1.0; extra == "dev"
Requires-Dist: mypy>=1.0.0; extra == "dev"
Requires-Dist: black>=23.0.0; extra == "dev"
Requires-Dist: isort>=5.12.0; extra == "dev"
Requires-Dist: flake8>=6.0.0; extra == "dev"
Dynamic: license-file
